{
  "project_info": {
    "project_number": "145088081009",
    "project_id": "stipra-108b2",
    "storage_bucket": "stipra-108b2.appspot.com"
  },
  "client": [
    {
      "client_info": {
        "mobilesdk_app_id": "1:145088081009:android:f8491e3ab1e652c66c7fd0",
        "android_client_info": {
          "package_name": "tekntrash.com.stipra"
        }
      },
      "oauth_client": [
        {
          "client_id": "145088081009-73a3393p65kvvhtse6pit96maki9ea30.apps.googleusercontent.com",
          "client_type": 1,
          "android_info": {
            "package_name": "tekntrash.com.stipra",
            "certificate_hash": "d34dd59d8c739104bb85464931dbb8cadbcd690c"
          }
        },
        {
          "client_id": "145088081009-f1dukrjm0vpi7f6n4qrpfd1pdu7c1gep.apps.googleusercontent.com",
          "client_type": 3
        }
      ],
      "api_key": [
        {
          "current_key": "AIzaSyC7oVWxLq_Qc5K-IRWh8JV181zmGoTwMEA"
        }
      ],
      "services": {
        "appinvite_service": {
          "other_platform_oauth_client": [
            {
              "client_id": "145088081009-f1dukrjm0vpi7f6n4qrpfd1pdu7c1gep.apps.googleusercontent.com",
              "client_type": 3
            }
          ]
        }
      }
    }
  ],
  "configuration_version": "1"
}